LICENSE
MANIFEST.in
README.md
build_requirements.txt
requirements.txt
setup.cfg
setup.py
ferris_sx/__init__.py
ferris_sx/agent.py
ferris_sx/core.py
ferris_sx/settings.py
ferris_sx/utils.py
ferris_sx.egg-info/PKG-INFO
ferris_sx.egg-info/SOURCES.txt
ferris_sx.egg-info/dependency_links.txt
ferris_sx.egg-info/not-zip-safe
ferris_sx.egg-info/requires.txt
ferris_sx.egg-info/top_level.txt